paper_neural/__init__.py
paper_neural/paper_siamese.py
paper_neural/paper_yolo_features.py
paper_neural/siamese_util.py
paper_neural/yolo_util.py
siamese/__init__.py
siamese/fibers_siamese.py
siamese/interface/__init__.py
siamese/interface/neural_interface.py
siamese/load_siamese.py
siamese/main.py
siamese/repository/__init__.py
siamese/repository/fibers_datasets.py
siamese/siameseapi.py
siamese/train_siamese.py
paper_neural-0.2.4.dist-info/LICENSE
paper_neural-0.2.4.dist-info/WHEEL
paper_neural-0.2.4.dist-info/METADATA
paper_neural-0.2.4.dist-info/RECORD
