Metadata-Version: 2.1
Name: paper-neural
Version: 0.2.4
Summary: Reunir mecanimos de detecção de fibras de segurança e comparação de features
Author: wagner
Author-email: rengaw.luiz@gmail.com
Requires-Python: >=3.9,<4.0
Classifier: Programming Language :: Python :: 3
Classifier: Programming Language :: Python :: 3.10
Classifier: Programming Language :: Python :: 3.9
Requires-Dist: Pillow (>=9.0.1,<10.0.0)
Requires-Dist: numpy (>=1.22.3,<2.0.0)
Requires-Dist: torch (>=1.8.2+cu111,<2.0.0)
